LICENSE
MANIFEST.in
README.md
setup.py
example/__init__.py
example/models.py
example/settings.py
example/urls.py
example/migrations/0001_initial.py
example/migrations/__init__.py
fef_questionnaire.egg-info/PKG-INFO
fef_questionnaire.egg-info/SOURCES.txt
fef_questionnaire.egg-info/dependency_links.txt
fef_questionnaire.egg-info/not-zip-safe
fef_questionnaire.egg-info/requires.txt
fef_questionnaire.egg-info/top_level.txt
questionnaire/__init__.py
questionnaire/admin.py
questionnaire/apps.py
questionnaire/dependency_checker.py
questionnaire/emails.py
questionnaire/forms.py
questionnaire/langtemplateloader.py
questionnaire/legacy_test_urls.py
questionnaire/legacy_tests.py
questionnaire/models.py
questionnaire/modelutils.py
questionnaire/parsers.py
questionnaire/profiler.py
questionnaire/request_cache.py
questionnaire/run.py
questionnaire/tests.py
questionnaire/urls.py
questionnaire/utils.py
questionnaire/utils_noncircular.py
questionnaire/views.py
questionnaire/context_processors/__init__.py
questionnaire/context_processors/settings.py
questionnaire/fixtures/.DS_Store
questionnaire/fixtures/sampleSurvey.json
questionnaire/fixtures/testQuestions.yaml
questionnaire/locale/.DS_Store
questionnaire/locale/de/.DS_Store
questionnaire/locale/de/LC_MESSAGES/django.po
questionnaire/locale/fr/LC_MESSAGES/django.po
questionnaire/locale/it/LC_MESSAGES/django.po
questionnaire/locale/ru/LC_MESSAGES/django.mo
questionnaire/locale/ru/LC_MESSAGES/django.po
questionnaire/management/__init__.py
questionnaire/management/commands/__init__.py
questionnaire/management/commands/make_landing_nonces.py
questionnaire/management/commands/questionnaire_emails.py
questionnaire/migrations/0001_initial.py
questionnaire/migrations/0002_auto_20160929_1320.py
questionnaire/migrations/0003_auto_20160929_1321.py
questionnaire/migrations/0004_auto_20160929_1800.py
questionnaire/migrations/__init__.py
questionnaire/page/__init__.py
questionnaire/page/admin.py
questionnaire/page/models.py
questionnaire/page/views.py
questionnaire/page/migrations/__init__.py
questionnaire/qprocessors/__init__.py
questionnaire/qprocessors/choice.py
questionnaire/qprocessors/custom.py
questionnaire/qprocessors/range_or_number.py
questionnaire/qprocessors/simple.py
