Metadata-Version: 2.1
Name: fef-questionnaire
Version: 6.0
Summary: A Django application for creating online questionnaires/surveys.
Home-page: https://github.com/EbookFoundation/fef-questionnaire
Author: Eldest Daughter, LLC., Free Ebook Foundation
Author-email: gcaprio@eldestdaughter.com, eric@hellman.net
License: BSD
Platform: UNKNOWN
Classifier: Development Status :: 4 - Beta
Classifier: Environment :: Web Environment
Classifier: Intended Audience :: Developers
Classifier: License :: OSI Approved :: BSD License
Classifier: Operating System :: OS Independent
Classifier: Programming Language :: Python
Classifier: Programming Language :: Python :: 2.7
Classifier: Programming Language :: Python :: 3.6
Classifier: Framework :: Django
